changelogfromtags/__init__.py
changelogfromtags/__main__.py
changelogfromtags/_version.py
changelogfromtags-0.5.0.dist-info/METADATA
changelogfromtags-0.5.0.dist-info/WHEEL
changelogfromtags-0.5.0.dist-info/entry_points.txt
changelogfromtags-0.5.0.dist-info/top_level.txt
changelogfromtags-0.5.0.dist-info/RECORD
